{
    "Ar36": {
        "error": 0.0014355558332376733,
        "error_type": "SEM",
        "filter_outliers_dict": {
            "filter_outliers": true,
            "iterations": 1,
            "std_devs": 3,
            "use_iqr_filtering": false,
            "use_standard_deviation_filtering": false
        },
        "fit": "linear",
        "fn": 27,
        "include_baseline_error": true,
        "n": 27,
        "outlier_excluded": [],
        "reviewed": true,
        "user_excluded": [],
        "value": 0.01724712901952043
    },
    "Ar37": {
        "error": 0.01982925798904389,
        "error_type": "SEM",
        "filter_outliers_dict": {
            "filter_outliers": true,
            "iterations": 1,
            "std_devs": 3,
            "use_iqr_filtering": false,
            "use_standard_deviation_filtering": false
        },
        "fit": "linear",
        "fn": 27,
        "include_baseline_error": true,
        "n": 27,
        "outlier_excluded": [],
        "reviewed": true,
        "user_excluded": [],
        "value": 0.07827196471228395
    },
    "Ar38": {
        "error": 0.024237854404400502,
        "error_type": "SEM",
        "filter_outliers_dict": {
            "filter_outliers": true,
            "iterations": 1,
            "std_devs": 3,
            "use_iqr_filtering": false,
            "use_standard_deviation_filtering": false
        },
        "fit": "linear",
        "fn": 27,
        "include_baseline_error": true,
        "n": 27,
        "outlier_excluded": [],
        "reviewed": true,
        "user_excluded": [],
        "value": 0.6349264782336819
    },
    "Ar39": {
        "error": 0.0695990023573393,
        "error_type": "SEM",
        "filter_outliers_dict": {
            "filter_outliers": true,
            "iterations": 1,
            "std_devs": 3,
            "use_iqr_filtering": false,
            "use_standard_deviation_filtering": false
        },
        "fit": "linear",
        "fn": 27,
        "include_baseline_error": true,
        "n": 27,
        "outlier_excluded": [],
        "reviewed": true,
        "user_excluded": [],
        "value": 49.818459186492305
    },
    "Ar40": {
        "error": 0.2929307400475961,
        "error_type": "SEM",
        "filter_outliers_dict": {
            "filter_outliers": true,
            "iterations": 1,
            "std_devs": 3,
            "use_iqr_filtering": false,
            "use_standard_deviation_filtering": false
        },
        "fit": "linear",
        "fn": 26,
        "include_baseline_error": true,
        "n": 27,
        "outlier_excluded": [
            14
        ],
        "reviewed": true,
        "user_excluded": [],
        "value": 1882.7774525313753
    },
    "Ar41": {
        "error": 0.23493932952096544,
        "error_type": "SEM",
        "filter_outliers_dict": {
            "filter_outliers": true,
            "iterations": 1,
            "std_devs": 2
        },
        "fit": "linear",
        "value": -0.8374321946094345
    }
}